slickpay_lib/__init__.py
slickpay_lib/constant.py
slickpay_lib/invoice.py
slickpay_lib/utils.py
slickpay_lib/sync_lib/__init__.py
slickpay_lib/sync_lib/webhook.py
slickpay_python-2.1.dist-info/LICENSE
slickpay_python-2.1.dist-info/METADATA
slickpay_python-2.1.dist-info/WHEEL
slickpay_python-2.1.dist-info/top_level.txt
slickpay_python-2.1.dist-info/RECORD
